chroma_vector_aggregator/__init__.py
chroma_vector_aggregator/aggregator.py
chroma_vector_aggregator/chroma_helpers.py
chroma_vector_aggregator/embedding_methods.py
chroma_vector_aggregator/utils.py
chroma_vector_aggregator-0.1.0.dist-info/LICENSE
chroma_vector_aggregator-0.1.0.dist-info/METADATA
chroma_vector_aggregator-0.1.0.dist-info/WHEEL
chroma_vector_aggregator-0.1.0.dist-info/top_level.txt
chroma_vector_aggregator-0.1.0.dist-info/RECORD
